[{"category":"corporation","id":1000002,"name":"CBD Corporation"},{"category":"corporation","id":1000003,"name":"Prompt Delivery"},{"category":"corporation","id":1000004,"name":"Ytiri"},{"category":"corporation","id":1000005,"name":"Hyasyoda Corporation"},{"category":"corporation","id":1000006,"name":"Deep Core Mining Inc."},{"category":"corporation","id":1000007,"name":"Poksu Mineral Group"},{"category":"corporation","id":1000008,"name":"Minedrill"},{"category":"corporation","id":1000009,"name":"Caldari Provisions"},{"category":"corporation","id":1000010,"name":"Kaalakiota Corporation"},{"category":"corporation","id":1000011,"name":"Wiyrkomi Corporation"},{"category":"corporation","id":1000012,"name":"Top Down"},{"category":"corporation","id":1000013,"name":"Rapid Assembly"},{"category":"corporation","id":1000014,"name":"Perkone"},{"category":"corporation","id":1000015,"name":"Caldari Steel"},{"category":"corporation","id":1000016,"name":"Zainou"},{"category":"corporation","id":1000017,"name":"Nugoeihuvi Corporation"},{"category":"corporation","id":1000018,"name":"Echelon Entertainment"},{"category":"corporation","id":1000019,"name":"Ishukone Corporation"},{"category":"corporation","id":1000020,"name":"Lai Dai Corporation"},{"category":"corporation","id":1000021,"name":"Zero-G Research Firm"},{"category":"corporation","id":1000022,"name":"Propel Dynamics"},{"category":"corporation","id":1000023,"name":"Expert Distribution"},{"category":"corporation","id":1000024,"name":"CBD Sell Division"},{"category":"corporation","id":1000025,"name":"Sukuuvestaa Corporation"},{"category":"corporation","id":1000026,"name":"Caldari Constructions"},{"category":"corporation","id":1000027,"name":"Expert Housing"},{"category":"corporation","id":1000028,"name":"Caldari Funds Unlimited"},{"category":"corporation","id":1000029,"name":"State and Region Bank"},{"category":"corporation","id":1000030,"name":"Modern Finances"},{"category":"corporation","id":1000031,"name":"Chief Executive Panel"},{"category":"corporation","id":1000032,"name":"Mercantile Club"},{"category":"corporation","id":1000033,"name":"Caldari Business Tribunal"},{"category":"corporation","id":1000034,"name":"House of Records"},{"category":"corporation","id":1000035,"name":"Caldari Navy"},{"category":"corporation","id":1000036,"name":"Internal Security"},{"category":"corporation","id":1000037,"name":"Lai Dai Protection Service"},{"category":"corporation","id":1000038,"name":"Ishukone Watch"},{"category":"corporation","id":1000039,"name":"Home Guard"},{"category":"corporation","id":1000040,"name":"Peace and Order Unit"},{"category":"corporation","id":1000041,"name":"Spacelane Patrol"},{"category":"corporation","id":1000042,"name":"Wiyrkomi Peace Corps"},{"category":"corporation","id":1000043,"name":"Corporate Police Force"},{"category":"corporation","id":1000044,"name":"School of Applied Knowledge"},{"category":"corporation","id":1000045,"name":"Science and Trade Institute"},{"category":"corporation","id":1000046,"name":"Sebiestor Tribe"},{"category":"corporation","id":1000047,"name":"Krusual Tribe"},{"category":"corporation","id":1000048,"name":"Vherokior Tribe"},{"category":"corporation","id":1000049,"name":"Brutor Tribe"},{"category":"corporation","id":1000050,"name":"Republic Parliament"},{"category":"corporation","id":1000051,"name":"Republic Fleet"},{"category":"corporation","id":1000052,"name":"Republic Justice Department"},{"category":"corporation","id":1000053,"name":"Urban Management"},{"category":"corporation","id":1000054,"name":"Republic Security Services"},{"category":"corporation","id":1000055,"name":"Minmatar Mining Corporation"},{"category":"corporation","id":1000056,"name":"Core Complexion Inc."},{"category":"corporation","id":1000057,"name":"Boundless Creation"},{"category":"corporation","id":1000058,"name":"Eifyr and Co."},{"category":"corporation","id":1000059,"name":"Six Kin Development"},{"category":"corporation","id":1000060,"name":"Native Freshfood"},{"category":"corporation","id":1000061,"name":"Freedom Extension"},{"category":"corporation","id":1000062,"name":"The Leisure Group"},{"category":"corporation","id":1000063,"name":"Amarr Constructions"},{"category":"corporation","id":1000064,"name":"Carthum Conglomerate"},{"category":"corporation","id":1000065,"name":"Imperial Armaments"},{"category":"corporation","id":1000066,"name":"Viziam"},{"category":"corporation","id":1000067,"name":"Zoar and Sons"},{"category":"corporation","id":1000068,"name":"Noble Appliances"},{"category":"corporation","id":1000069,"name":"Ducia Foundry"},{"category":"corporation","id":1000070,"name":"HZO Refinery"},{"category":"corporation","id":1000071,"name":"Inherent Implants"},{"category":"corporation","id":1000072,"name":"Imperial Shipment"},{"category":"corporation","id":1000073,"name":"Amarr Certified News"},{"category":"corporation","id":1000074,"name":"Joint Harvesting"},{"category":"corporation","id":1000075,"name":"Nurtura"},{"category":"corporation","id":1000076,"name":"Further Foodstuffs"},{"category":"corporation","id":1000077,"name":"Royal Amarr Institute"},{"category":"corporation","id":1000078,"name":"Imperial Chancellor"},{"category":"corporation","id":1000079,"name":"Amarr Civil Service"},{"category":"corporation","id":1000080,"name":"Ministry of War"},{"category":"corporation","id":1000081,"name":"Ministry of Assessment"},{"category":"corporation","id":1000082,"name":"Ministry of Internal Order"},{"category":"corporation","id":1000083,"name":"Amarr Trade Registry"},{"category":"corporation","id":1000084,"name":"Amarr Navy"},{"category":"corporation","id":1000085,"name":"Court Chamberlain"},{"category":"corporation","id":1000086,"name":"Emperor Family"},{"category":"corporation","id":1000087,"name":"Kador Family"},{"category":"corporation","id":1000088,"name":"Sarum Family"},{"category":"corporation","id":1000089,"name":"Kor-Azor Family"},{"category":"corporation","id":1000090,"name":"Ardishapur Family"},{"category":"corporation","id":1000091,"name":"Tash-Murkon Family"},{"category":"corporation","id":1000092,"name":"Civic Court"},{"category":"corporation","id":1000093,"name":"Theology Council"},{"category":"corporation","id":1000094,"name":"TransStellar Shipping"},{"category":"corporation","id":1000095,"name":"Federal Freight"},{"category":"corporation","id":1000096,"name":"Inner Zone Shipping"},{"category":"corporation","id":1000097,"name":"Material Acquisition"},{"category":"corporation","id":1000098,"name":"Astral Mining Inc."},{"category":"corporation","id":1000099,"name":"Combined Harvest"},{"category":"corporation","id":1000100,"name":"Quafe Company"},{"category":"corporation","id":1000101,"name":"CreoDron"},{"category":"corporation","id":1000102,"name":"Roden Shipyards"},{"category":"corporation","id":1000103,"name":"Allotek Industries"},{"category":"corporation","id":1000104,"name":"Poteque Pharmaceuticals"},{"category":"corporation","id":1000105,"name":"Impetus"},{"category":"corporation","id":1000106,"name":"Egonics Inc."},{"category":"corporation","id":1000107,"name":"The Scope"},{"category":"corporation","id":1000108,"name":"Chemal Tech"},{"category":"corporation","id":1000109,"name":"Duvolle Laboratories"},{"category":"corporation","id":1000110,"name":"FedMart"},{"category":"corporation","id":1000111,"name":"Aliastra"},{"category":"corporation","id":1000112,"name":"Bank of Luminaire"},{"category":"corporation","id":1000113,"name":"Pend Insurance"},{"category":"corporation","id":1000114,"name":"Garoun Investment Bank"},{"category":"corporation","id":1000115,"name":"University of Caille"},{"category":"corporation","id":1000116,"name":"President"},{"category":"corporation","id":1000117,"name":"Senate"},{"category":"corporation","id":1000118,"name":"Supreme Court"},{"category":"corporation","id":1000119,"name":"Federal Administration"},{"category":"corporation","id":1000120,"name":"Federation Navy"},{"category":"corporation","id":1000121,"name":"Federal Intelligence Office"},{"category":"corporation","id":1000122,"name":"Federation Customs"},{"category":"corporation","id":1000123,"name":"Ammatar Fleet"},{"category":"corporation","id":1000124,"name":"Archangels"},{"category":"corporation","id":1000125,"name":"CONCORD"},{"category":"corporation","id":1000126,"name":"Ammatar Consulate"},{"category":"corporation","id":1000127,"name":"Guristas"},{"category":"corporation","id":1000128,"name":"Mordu's Legion"},{"category":"corporation","id":1000129,"name":"Outer Ring Excavations"},{"category":"corporation","id":1000130,"name":"Sisters of EVE"},{"category":"corporation","id":1000133,"name":"Salvation Angels"},{"category":"corporation","id":1000134,"name":"Blood Raiders"},{"category":"corporation","id":1000135,"name":"Serpentis Corporation"},{"category":"corporation","id":1000136,"name":"Guardian Angels"},{"category":"corporation","id":1000137,"name":"DED"},{"category":"corporation","id":1000138,"name":"Dominations"},{"category":"corporation","id":1000139,"name":"Food Relief"},{"category":"corporation","id":1000141,"name":"Guristas Production"},{"category":"corporation","id":1000144,"name":"Intaki Bank"},{"category":"corporation","id":1000145,"name":"Intaki Commerce"},{"category":"corporation","id":1000146,"name":"Intaki Space Police"},{"category":"corporation","id":1000147,"name":"Intaki Syndicate"},{"category":"corporation","id":1000151,"name":"Khanid Innovation"},{"category":"corporation","id":1000152,"name":"Khanid Transport"},{"category":"corporation","id":1000153,"name":"Khanid Works"},{"category":"corporation","id":1000154,"name":"Nefantar Miner Association"},{"category":"corporation","id":1000156,"name":"Royal Khanid Navy"},{"category":"corporation","id":1000157,"name":"Serpentis Inquest"},{"category":"corporation","id":1000159,"name":"The Sanctuary"},{"category":"corporation","id":1000160,"name":"Thukker Mix"},{"category":"corporation","id":1000161,"name":"True Creations"},{"category":"corporation","id":1000162,"name":"True Power"},{"category":"corporation","id":1000163,"name":"Trust Partners"},{"category":"corporation","id":1000165,"name":"Hedion University"},{"category":"corporation","id":1000166,"name":"Imperial Academy"},{"category":"corporation","id":1000167,"name":"State War Academy"},{"category":"corporation","id":1000168,"name":"Federal Navy Academy"},{"category":"corporation","id":1000169,"name":"Center for Advanced Studies"},{"category":"corporation","id":1000170,"name":"Republic Military School"},{"category":"corporation","id":1000171,"name":"Republic University"},{"category":"corporation","id":1000172,"name":"Pator Tech School"},{"category":"corporation","id":1000179,"name":"24th Imperial Crusade"},{"category":"corporation","id":1000180,"name":"State Protectorate"},{"category":"corporation","id":1000181,"name":"Federal Defense Union"},{"category":"corporation","id":1000182,"name":"Tribal Liberation Force"},{"category":"corporation","id":1000270,"name":"Outer Ring Development"},{"category":"corporation","id":1000271,"name":"Outer Ring Prospecting"},{"category":"corporation","id":1000276,"name":"ORE Technologies"},{"category":"corporation","id":1000277,"name":"Frostline Laboratories"},{"category":"corporation","id":1000283,"name":"Imperial War Reserves"},{"category":"corporation","id":1000284,"name":"State Military Stockpile"},{"category":"corporation","id":1000285,"name":"Federal Strategic Materiel"},{"category":"corporation","id":1000286,"name":"Republic Fleet Ordnance"}]